streamlit_yellowbrick/__init__.py
streamlit_yellowbrick-0.0.3.dist-info/LICENSE
streamlit_yellowbrick-0.0.3.dist-info/METADATA
streamlit_yellowbrick-0.0.3.dist-info/WHEEL
streamlit_yellowbrick-0.0.3.dist-info/top_level.txt
streamlit_yellowbrick-0.0.3.dist-info/RECORD
