Metadata-Version: 2.1
Name: streamlit-yellowbrick
Version: 0.0.3
Summary: Streamlit component for Yellowbrick visualization library
Home-page: https://github.com/snehankekre/streamlit-yellowbrick
Author: Snehan Kekre
Author-email: snehan@streamlit.io
License: UNKNOWN
Platform: UNKNOWN
Requires-Python: >=3.6
License-File: LICENSE
Requires-Dist: streamlit (>=0.63)
Requires-Dist: yellowbrick
